{
  "Data 1" : {
    "outputString" : "asdf",
    "numberOfData" : 1
  },
  "Data 2" : {
    "outputString" : "adsf",
    "numberOfData" : 2
  },
  "Data 3" : {
    "outputString" : "asdf",
    "numberOfData" : 3
  },
  "Data 4" : {
    "outputString" : "asdf",
    "numberOfData" : 4
  },
  "Data 5" : {
    "outputString" : "adsf",
    "numberOfData" : 5
  },
  "Data 6" : {
    "outputString" : "asdf",
    "numberOfData" : 6
  },
  "Data 7" : {
    "outputString" : "adf",
    "numberOfData" : 7
  },
  "Data 8" : {
    "outputString" : "asdf",
    "numberOfData" : 8
  },
  "Data 9" : {
    "outputString" : "asdf",
    "numberOfData" : 9
  },
  "Data 10" : {
    "outputString" : "asdf",
    "numberOfData" : 10
  }
}